deeco/__init__.py
deeco/core.py
deeco/mapping.py
deeco/packets.py
deeco/plugins/__init__.py
deeco/plugins/ensemblereactor.py
deeco/plugins/identity_replicas.py
deeco/plugins/knowledgepublisher.py
deeco/plugins/positionprovider.py
deeco/plugins/replicas.py
deeco/plugins/simplenetwork.py
deeco/plugins/snapshoter.py
deeco/plugins/walker.py
deeco/position.py
deeco/runnable.py
deeco/sim.py
deeco/simloader.py
hospital_world/__init__.py
hospital_world/a_lab_samples_scenario.py
hospital_world/bindings.py
hospital_world/hospital_map.py
hospital_world/lab_samples_mission.py
mission_control/__init__.py
mission_control/common_descriptors/__init__.py
mission_control/common_descriptors/generic_constant_cost_sd.py
mission_control/common_descriptors/navigation_sd.py
mission_control/common_descriptors/routes_ed.py
mission_control/coordination/__init__.py
mission_control/coordination/coalition_formation.py
mission_control/coordination/integration.py
mission_control/coordination/planning.py
mission_control/coordination/repair.py
mission_control/coordination/supervision.py
mission_control/coordination/update_mission.py
mission_control/data_model/__init__.py
mission_control/data_model/ihtn.py
mission_control/data_model/ihtn_algorithms.py
mission_control/data_model/restrictions.py
mission_control/data_model/world_model.py
mission_control/deeco_integration/__init__.py
mission_control/deeco_integration/client.py
mission_control/deeco_integration/coordinator.py
mission_control/deeco_integration/deeco_timer.py
mission_control/deeco_integration/mission_coordination_ensemble.py
mission_control/deeco_integration/plugins/__init__.py
mission_control/deeco_integration/plugins/hande_request_service.py
mission_control/deeco_integration/plugins/requests_queue.py
mission_control/deeco_integration/plugins/service.py
mission_control/deeco_integration/plugins/workload.py
mission_control/deeco_integration/requests_ensemble.py
mission_control/deeco_integration/requests_server_component.py
hmrs_mission_control-1.1.1.dist-info/WHEEL
hmrs_mission_control-1.1.1.dist-info/METADATA
hmrs_mission_control-1.1.1.dist-info/RECORD
