Metadata-Version: 2.1
Name: hmrs-mission-control
Version: 1.1.1
Summary: **Heterogeneous Multi-Robots Mission Control** is an architecture for the development of applications, capable of coordinating multi-robot missions subject to uncertainty in properties of the available robots in the Software Engineering Lab (LES) at University of Brasilia.
License: MIT
Author: Gabriel Rodrigues
Author-email: gabrielsr@gmail.com
Requires-Python: >=3.10,<4.0
Classifier: License :: OSI Approved :: MIT License
Classifier: Programming Language :: Python :: 3
Classifier: Programming Language :: Python :: 3.10
Requires-Dist: PyQt5 (>=5.15.6,<6.0.0)
Requires-Dist: jsonpickle (>=2.2.0,<3.0.0)
Requires-Dist: lagom (>=1.7.0,<2.0.0)
Requires-Dist: lxml (>=4.8.0,<5.0.0)
Requires-Dist: matplotlib (>=3.5.2,<4.0.0)
Requires-Dist: setuptools (>=62.3.2,<63.0.0)
Requires-Dist: shortuuid (>=1.0.9,<2.0.0)
Project-URL: Bug Tracker, https://github.com/lesunb/hmrs_mission_control/issues
